parsers/__init__.py
parsers/date_parser.py
parsers/ip_parser.py
parsers/log_parser.py
parsers/time_parser.py
custom_parser_hiba_khabar-1.0.0.dist-info/METADATA
custom_parser_hiba_khabar-1.0.0.dist-info/WHEEL
custom_parser_hiba_khabar-1.0.0.dist-info/top_level.txt
custom_parser_hiba_khabar-1.0.0.dist-info/RECORD
