Metadata-Version: 2.4
Name: custom_parser_hiba_khabar
Version: 1.0.0
Summary: A simple IPv4 log parser using regex, created by hiba khabar, file handling, and data structures.
Author-email: khabar Hiba <hibakhabar@gmail.com>
License: MIT
Requires-Python: >=3.8
